<?xml version="1.0" encoding="UTF-8"?>

<!-- generated on 2023-10-16 19:19:41 by Eclipse SUMO GUI Version 1.18.0
<configuration xmlns:xsi="http://www.w3.org/2001/XMLSchema-instance" xsi:noNamespaceSchemaLocation="http://sumo.dlr.de/xsd/sumoConfiguration.xsd">

    <input>
        <net-file value="/Users/sindhujach/Desktop/ECE 699/(No subject)/new.net.xml"/>
        <route-files value="simulation_outputs/modified_EGO_VEHTYPE_tau=0.5.xml"/>
    </input>

    <output>
        <collision-output value="simulation_outputs/output_tau=0.5_run_2.xml"/>
    </output>

    <time>
        <begin value="0"/>
        <end value="500"/>
    </time>

    <traci_server>
        <remote-port value="54013"/>
    </traci_server>

    <random_number>
        <random value="true"/>
    </random_number>

</configuration>
-->

<collisions xmlns:xsi="http://www.w3.org/2001/XMLSchema-instance" xsi:noNamespaceSchemaLocation="http://sumo.dlr.de/xsd/collision_file.xsd">
    <collision time="272.00" type="collision" lane="E28_0" pos="39.79" collider="f_0_ego.9" victim="f_0_default.10" colliderType="EGO_VEHTYPE" victimType="DEFAULT_VEHTYPE" colliderSpeed="1.61" victimSpeed="0.00"/>
    <collision time="308.00" type="collision" lane="E28_0" pos="117.55" collider="f_0_default.21" victim="f_0_ego.23" colliderType="DEFAULT_VEHTYPE" victimType="EGO_VEHTYPE" colliderSpeed="5.21" victimSpeed="0.00"/>
    <collision time="312.00" type="collision" lane="E28_0" pos="88.76" collider="f_0_ego.18" victim="f_0_ego.12" colliderType="EGO_VEHTYPE" victimType="EGO_VEHTYPE" colliderSpeed="7.76" victimSpeed="0.00"/>
</collisions>
